agnostic_calculator-1.1.0.dist-info/METADATA
agnostic_calculator-1.1.0.dist-info/RECORD
agnostic_calculator-1.1.0.dist-info/WHEEL
agnostic_calculator-1.1.0.dist-info/top_level.txt
calculator/__init__.py
calculator/calculator.py
calculator/test_calculator.py
calculator/converters/__init__.py
calculator/converters/roman.py
calculator/converters/test_roman.py
